openweathermaps/__init__.py
openweathermaps/test.py
openweathermaps/OpenWeatherMapBase/__init__.py
openweathermaps/OpenWeatherMapBase/open_weather_map_base.py
py_owm_base-1.0.0.dist-info/LICENSE.txt
py_owm_base-1.0.0.dist-info/METADATA
py_owm_base-1.0.0.dist-info/WHEEL
py_owm_base-1.0.0.dist-info/top_level.txt
py_owm_base-1.0.0.dist-info/RECORD
